pswgen/__init__.py
pswgen/__main__.py
pswgen-1.0.0.dist-info/METADATA
pswgen-1.0.0.dist-info/WHEEL
pswgen-1.0.0.dist-info/entry_points.txt
pswgen-1.0.0.dist-info/top_level.txt
pswgen-1.0.0.dist-info/RECORD
