Metadata-Version: 2.1
Name: pswgen
Version: 1.0.0
Summary: A simple and easy program to generate secure passwords.
Home-page: UNKNOWN
Author: Elia Toselli
Author-email: elia.toselli@outlook.it
License: UNKNOWN
Platform: UNKNOWN
